README.md
setup.py
baidubot/__init__.py
baidubot.egg-info/PKG-INFO
baidubot.egg-info/SOURCES.txt
baidubot.egg-info/dependency_links.txt
baidubot.egg-info/requires.txt
baidubot.egg-info/top_level.txt