Metadata-Version: 1.0
Name: baidubot
Version: 0.1.1
Summary: A simple Python module to scrape search results from Baidu
Home-page: https://github.com/EdmundMartin/
Author: Edmund Martin
Author-email: edmartin101@googlemail.com
License: UNKNOWN
Keywords: baidu,scraping
Platform: UNKNOWN
